lxmlx/__init__.py
lxmlx/event.py
lxmlx/validate.py
lxmlx/xml_writer.py
lxmlx-2.0.1.dist-info/LICENSE
lxmlx-2.0.1.dist-info/METADATA
lxmlx-2.0.1.dist-info/WHEEL
lxmlx-2.0.1.dist-info/top_level.txt
lxmlx-2.0.1.dist-info/RECORD
